ac_solver/__init__.py
ac_solver/agents/__init__.py
ac_solver/agents/args.py
ac_solver/agents/environment.py
ac_solver/agents/ppo.py
ac_solver/agents/ppo_agent.py
ac_solver/agents/training.py
ac_solver/agents/utils.py
ac_solver/envs/__init__.py
ac_solver/envs/ac_env.py
ac_solver/envs/ac_moves.py
ac_solver/envs/utils.py
ac_solver/search/__init__.py
ac_solver/search/breadth_first.py
ac_solver/search/greedy.py
ac_solver/search/miller_schupp/__init__.py
ac_solver/search/miller_schupp/data/.DS_Store
ac_solver/search/miller_schupp/data/__init__.py
ac_solver/search/miller_schupp/data/all_presentations.txt
ac_solver/search/miller_schupp/data/bfs_solved_presentations.txt
ac_solver/search/miller_schupp/data/greedy_search_paths.txt
ac_solver/search/miller_schupp/data/greedy_solved_presentations.txt
ac_solver/search/miller_schupp/data/n-1-to-2_lenw-1-to-2-max-nodes-10000-bfs_paths.txt
ac_solver/search/miller_schupp/data/n-1-to-2_lenw-1-to-2-max-nodes-10000-bfs_solved.txt
ac_solver/search/miller_schupp/data/n-1-to-2_lenw-1-to-2-max-nodes-10000-bfs_unsolved.txt
ac_solver/search/miller_schupp/data/n-1-to-2_lenw-1-to-2-max-nodes-1000000-bfs_paths.txt
ac_solver/search/miller_schupp/data/n-1-to-2_lenw-1-to-2-max-nodes-1000000-bfs_solved.txt
ac_solver/search/miller_schupp/data/n-1-to-2_lenw-1-to-2-max-nodes-1000000-bfs_unsolved.txt
ac_solver/search/miller_schupp/data/n-1-to-3_lenw-1-to-3-greedy_search_paths.txt
ac_solver/search/miller_schupp/data/n-1-to-3_lenw-1-to-3-greedy_search_solved.txt
ac_solver/search/miller_schupp/data/n-1-to-3_lenw-1-to-3-greedy_search_unsolved.txt
ac_solver/search/miller_schupp/data/n-3-to-4_lenw-1-to-3-greedy_search_paths.txt
ac_solver/search/miller_schupp/data/n-3-to-4_lenw-1-to-3-greedy_search_solved.txt
ac_solver/search/miller_schupp/data/n-3-to-4_lenw-1-to-3-greedy_search_unsolved.txt
ac_solver/search/miller_schupp/data/n-3-to-4_lenw-1-to-4-max-nodes-25000-greedy_search_paths.txt
ac_solver-0.1.0.dist-info/LICENSE.md
ac_solver-0.1.0.dist-info/METADATA
ac_solver-0.1.0.dist-info/WHEEL
ac_solver-0.1.0.dist-info/RECORD
