Metadata-Version: 2.1
Name: ac_solver
Version: 0.1.0
Summary: 
Author: shehper
Author-email: ali.shehper1@gmail.com
Requires-Python: >=3.9,<3.12
Classifier: Programming Language :: Python :: 3
Classifier: Programming Language :: Python :: 3.9
Classifier: Programming Language :: Python :: 3.10
Classifier: Programming Language :: Python :: 3.11
Requires-Dist: Farama-Notifications (==0.0.4)
Requires-Dist: GitPython (==3.1.43)
Requires-Dist: Jinja2 (==3.1.4)
Requires-Dist: MarkupSafe (==2.1.5)
Requires-Dist: PyYAML (==6.0.2)
Requires-Dist: Pygments (==2.18.0)
Requires-Dist: appdirs (==1.4.4)
Requires-Dist: appnope (==0.1.4)
Requires-Dist: asttokens (==2.4.1)
Requires-Dist: attrs (==24.2.0)
Requires-Dist: certifi (==2024.7.4)
Requires-Dist: charset-normalizer (==3.3.2)
Requires-Dist: click (==8.1.7)
Requires-Dist: cloudpickle (==3.0.0)
Requires-Dist: comm (==0.2.2)
Requires-Dist: contourpy (==1.2.1)
Requires-Dist: cycler (==0.12.1)
Requires-Dist: debugpy (==1.8.5)
Requires-Dist: decorator (==5.1.1)
Requires-Dist: docker-pycreds (==0.4.0)
Requires-Dist: exceptiongroup (==1.2.2)
Requires-Dist: executing (==2.0.1)
Requires-Dist: fastjsonschema (==2.20.0)
Requires-Dist: filelock (==3.15.4)
Requires-Dist: fonttools (==4.53.1)
Requires-Dist: gitdb (==4.0.11)
Requires-Dist: gymnasium (==0.28.1)
Requires-Dist: idna (==3.8)
Requires-Dist: importlib_metadata (==8.4.0)
Requires-Dist: importlib_resources (==6.4.4)
Requires-Dist: ipykernel (==6.29.5)
Requires-Dist: ipython (==8.18.1)
Requires-Dist: jax-jumpy (==1.0.0)
Requires-Dist: jedi (==0.19.1)
Requires-Dist: joblib (==1.4.2)
Requires-Dist: jsonschema (==4.23.0)
Requires-Dist: jsonschema-specifications (==2023.12.1)
Requires-Dist: jupyter_client (==8.6.2)
Requires-Dist: jupyter_core (==5.7.2)
Requires-Dist: kaleido (==0.2.1)
Requires-Dist: kiwisolver (==1.4.5)
Requires-Dist: matplotlib (==3.7.1)
Requires-Dist: matplotlib-inline (==0.1.7)
Requires-Dist: mpmath (==1.3.0)
Requires-Dist: nbformat (==5.8.0)
Requires-Dist: nest-asyncio (==1.6.0)
Requires-Dist: networkx (==3.2.1)
Requires-Dist: numpy (==1.24.3)
Requires-Dist: packaging (==24.1)
Requires-Dist: parso (==0.8.4)
Requires-Dist: pathtools (==0.1.2)
Requires-Dist: pexpect (==4.9.0)
Requires-Dist: pillow (==10.4.0)
Requires-Dist: platformdirs (==4.2.2)
Requires-Dist: plotly (==5.18.0)
Requires-Dist: prompt_toolkit (==3.0.47)
Requires-Dist: protobuf (==4.25.4)
Requires-Dist: psutil (==6.0.0)
Requires-Dist: ptyprocess (==0.7.0)
Requires-Dist: pure_eval (==0.2.3)
Requires-Dist: pyparsing (==3.1.4)
Requires-Dist: python-dateutil (==2.9.0.post0)
Requires-Dist: pyzmq (==26.2.0)
Requires-Dist: referencing (==0.35.1)
Requires-Dist: requests (==2.32.3)
Requires-Dist: rpds-py (==0.20.0)
Requires-Dist: scikit-learn (==1.3.1)
Requires-Dist: scipy (==1.13.1)
Requires-Dist: sentry-sdk (==2.13.0)
Requires-Dist: setproctitle (==1.3.3)
Requires-Dist: six (==1.16.0)
Requires-Dist: smmap (==5.0.1)
Requires-Dist: stack-data (==0.6.3)
Requires-Dist: sympy (==1.13.2)
Requires-Dist: tenacity (==9.0.0)
Requires-Dist: threadpoolctl (==3.5.0)
Requires-Dist: torch (==2.0.1)
Requires-Dist: tornado (==6.4.1)
Requires-Dist: tqdm (==4.65.0)
Requires-Dist: traitlets (==5.14.3)
Requires-Dist: typing_extensions (==4.12.2)
Requires-Dist: urllib3 (==2.2.2)
Requires-Dist: wandb (==0.15.3)
Requires-Dist: wcwidth (==0.2.13)
Requires-Dist: zipp (==3.20.1)
